elib/__init__.py
elib/django/__init__.py
elib/django/admin.py
elib/django/db.py
elib/django/http.py
elib/django/template.py
elib/django/wsgi.py
elib/django/management/__init__.py
elib/django/management/commands/__init__.py
elib/django/management/commands/celery.py
elib/django/management/commands/gunicorn.py
elib_django-0.0.11.dist-info/METADATA
elib_django-0.0.11.dist-info/WHEEL
elib_django-0.0.11.dist-info/top_level.txt
elib_django-0.0.11.dist-info/RECORD
